pollination_streamlit_viewer/__init__.py
pollination_streamlit_viewer/frontend/.env
pollination_streamlit_viewer/frontend/.prettierrc
pollination_streamlit_viewer/frontend/craco.config.js
pollination_streamlit_viewer/frontend/package.json
pollination_streamlit_viewer/frontend/tsconfig.json
pollination_streamlit_viewer/frontend/yarn.lock
pollination_streamlit_viewer/frontend/build/asset-manifest.json
pollination_streamlit_viewer/frontend/build/index.html
pollination_streamlit_viewer/frontend/build/static/css/main.b6a6f5c7.css
pollination_streamlit_viewer/frontend/build/static/css/main.b6a6f5c7.css.map
pollination_streamlit_viewer/frontend/build/static/js/main.eb30a1dd.js
pollination_streamlit_viewer/frontend/build/static/js/main.eb30a1dd.js.LICENSE.txt
pollination_streamlit_viewer/frontend/build/static/js/main.eb30a1dd.js.map
pollination_streamlit_viewer/frontend/public/index.html
pollination_streamlit_viewer/frontend/src/VTKStreamlit.css
pollination_streamlit_viewer/frontend/src/VTKStreamlit.tsx
pollination_streamlit_viewer/frontend/src/index.tsx
pollination_streamlit_viewer/frontend/src/react-app-env.d.ts
pollination_streamlit_viewer-0.5.1.dist-info/LICENSE
pollination_streamlit_viewer-0.5.1.dist-info/METADATA
pollination_streamlit_viewer-0.5.1.dist-info/WHEEL
pollination_streamlit_viewer-0.5.1.dist-info/top_level.txt
pollination_streamlit_viewer-0.5.1.dist-info/RECORD
