Metadata-Version: 2.1
Name: pollination-streamlit-viewer
Version: 0.5.1
Summary: vtkjs component for streamlit
Home-page: https://github.com/pollination/pollination-streamlit-viewer
Author: Pollination
Author-email: nicolas@ladybug.tools
Requires-Python: >=3.7
License-File: LICENSE
Requires-Dist: streamlit >=1.5.1
